django_goals/__init__.py
django_goals/admin.py
django_goals/admin_tests.py
django_goals/apps.py
django_goals/blocking_worker.py
django_goals/busy_worker.py
django_goals/busy_worker_tests.py
django_goals/conftest.py
django_goals/factories.py
django_goals/limits.py
django_goals/management/__init__.py
django_goals/management/commands/__init__.py
django_goals/management/commands/goals_blocking_worker.py
django_goals/management/commands/goals_busy_worker.py
django_goals/management/commands/goals_busy_worker_tests.py
django_goals/management/commands/goals_fsck.py
django_goals/management/commands/goals_fsck_tests.py
django_goals/management/commands/goals_retry.py
django_goals/management/commands/goals_threaded_worker.py
django_goals/management/commands/goals_threaded_worker_tests.py
django_goals/management/commands/set_goal.py
django_goals/management/commands/set_goal_tests.py
django_goals/migrations/0001_initial.py
django_goals/migrations/0002_goalprogress_message.py
django_goals/migrations/0003_remove_goal_goals_waiting_for_worker_idx_and_more.py
django_goals/migrations/0004_goal_waiting_for_count.py
django_goals/migrations/0005_goal_goals_waiting_for_precond_idx.py
django_goals/migrations/0006_goal_waiting_for_failed_count_and_more.py
django_goals/migrations/0007_goal_goals_achieved_idx.py
django_goals/migrations/0008_remove_goal_goals_waiting_for_precond_idx_and_more.py
django_goals/migrations/0009_goal_waiting_for_not_achieved_count.py
django_goals/migrations/0010_remove_goal_goals_waiting_for_failed_idx_and_more.py
django_goals/migrations/0011_goalpickup.py
django_goals/migrations/__init__.py
django_goals/models.py
django_goals/models_tests.py
django_goals/notifications.py
django_goals/notifications_tests.py
django_goals/pickups.py
django_goals/sentry.py
django_goals/utils.py
django_goals/worker_tests.py
django_goals-0.7.4.dist-info/LICENSE
django_goals-0.7.4.dist-info/METADATA
django_goals-0.7.4.dist-info/WHEEL
django_goals-0.7.4.dist-info/RECORD
