Metadata-Version: 2.3
Name: django-goals
Version: 0.7.4
Summary: 
License: MIT
Requires-Python: >=3.13,<4.0
Classifier: License :: OSI Approved :: MIT License
Classifier: Programming Language :: Python :: 3
Classifier: Programming Language :: Python :: 3.13
Requires-Dist: django (>=4.2)
Requires-Dist: django-object-actions (>=4.3)
Project-URL: Repository, https://github.com/EE/django-goals
